django_pyuwsgi/__init__.py
django_pyuwsgi/management/__init__.py
django_pyuwsgi/management/commands/__init__.py
django_pyuwsgi/management/commands/pyuwsgi.py
django_pyuwsgi/tests/__init__.py
django_pyuwsgi/tests/django_settings.py
django_pyuwsgi/tests/tests.py
django_pyuwsgi-1.1.1.dist-info/METADATA
django_pyuwsgi-1.1.1.dist-info/RECORD
django_pyuwsgi-1.1.1.dist-info/WHEEL
django_pyuwsgi-1.1.1.dist-info/top_level.txt
