Metadata-Version: 2.1
Name: django-pyuwsgi
Version: 1.1.1
Summary: uWSGI as a Django management command
Home-page: https://github.com/lincolnloop/django-pyuwsgi
Author: Peter Baumgartner
Author-email: pete@lincolnloop.com
License: MIT
Keywords: uwsgi,django,pyuwsgi
Platform: UNKNOWN
Classifier: Development Status :: 4 - Beta
Classifier: Intended Audience :: Developers
Classifier: License :: OSI Approved :: MIT License
Classifier: Programming Language :: Python
Classifier: Programming Language :: Python :: 2.7
Classifier: Programming Language :: Python :: 3.5
Classifier: Programming Language :: Python :: 3.6
Classifier: Programming Language :: Python :: 3.7
Classifier: Framework :: Django
Provides-Extra: test
Requires-Dist: pyuwsgi (>=2.0.17.2b3)
Requires-Dist: Django
Provides-Extra: test
Requires-Dist: pytest; extra == 'test'
